[{"link":"https:\/\/www.vogue.com\/fashion-shows\/fall-2025-menswear\/acne-studios","title":"Acne Studios Fall 2025 Menswear","ch":"Vogue","date":1737609011,"image":"https:\/\/assets.vogue.com\/photos\/678e8765ca5c972b0d3fe883\/master\/pass\/00001-acne-studios-fall-2025-menswear-credit-brand.jpg","audio":""},{"link":"https:\/\/www.vogue.com\/fashion-shows\/pre-fall-2025\/cecilie-bahnsen","title":"Cecilie Bahnsen Pre-Fall 2025","ch":"Vogue","date":1737609011,"image":"https:\/\/assets.vogue.com\/photos\/6791066072322234156212b4\/master\/pass\/00001-cecilie-bahnsen-pre-fall-2025-credit-brand.jpg","audio":""},{"link":"https:\/\/www.vogue.com\/fashion-shows\/fall-2025-menswear\/ernest-w-baker","title":"Ernest W. Baker Fall 2025 Menswear","ch":"Vogue","date":1737609011,"image":"https:\/\/assets.vogue.com\/photos\/678f7374491eb5a77026f3fa\/master\/pass\/00001-ernest-baker-fall-2025-menswear-credit-brand.jpg","audio":""},{"link":"https:\/\/www.vogue.com\/fashion-shows\/fall-2025-menswear\/paul-smith","title":"Paul Smith Fall 2025 Menswear","ch":"Vogue","date":1737609011,"image":"https:\/\/assets.vogue.com\/photos\/679110db806238aa95500667\/master\/pass\/00001-paul-smith-fall-2025-menswear-credit-brand.jpg","audio":""},{"link":"https:\/\/hypebeast.cn\/2025\/1\/national-baseball-hall-of-fame-and-museum-ichiro-suzuki","title":"\u4e9a\u6d32\u7b2c\u4e00\u4eba\uff01\u94c3\u6728\u4e00\u6717\u5165\u9009\u7f8e\u56fd\u68d2\u7403\u540d\u4eba\u5802","ch":"Hypebeast","date":1737609010,"image":"https:\/\/image-cdn.hypb.st\/https%3A%2F%2Fhypebeast.com%2Fwp-content%2Fblogs.dir%2F4%2Ffiles%2F2025%2F01%2F23%2Fhttps___hk.hypebeast.com_files_2025_01_22_national-baseball-hall-of-fame-and-museum-ichiro-suzuki-0001-scaled-2.jpg?w=800&cbr=1&q=90&fit=max","audio":""},{"link":"https:\/\/hypebeast.cn\/2025\/1\/hoka-speed-loafer-release-date","title":"HOKA \u63a8\u51fa\u5168\u65b0 Speed Loafer \u4e50\u798f\u978b\u6b3e","ch":"Hypebeast","date":1737608844,"image":"https:\/\/image-cdn.hypb.st\/https%3A%2F%2Fhypebeast.com%2Fwp-content%2Fblogs.dir%2F4%2Ffiles%2F2025%2F01%2F23%2Fhttps___hk.hypebeast.com_files_2025_01_23_hoka-speed-loafer-release-date-0.jpg?w=800&cbr=1&q=90&fit=max","audio":""},{"link":"https:\/\/hypebeast.cn\/2025\/1\/mithridate-daniel-fletcher-creative-director-announcement-info","title":"MITHRIDATE \u5ba3\u5e03 Daniel Fletcher \u6210\u4e3a\u65b0\u4efb\u521b\u610f\u603b\u76d1","ch":"Hypebeast","date":1737608594,"image":"https:\/\/image-cdn.hypb.st\/https%3A%2F%2Fhypebeast.com%2Fwp-content%2Fblogs.dir%2F4%2Ffiles%2F2025%2F01%2F23%2Fmithridate-daniel-fletcher-creative-director-announcement-info-0.jpg?w=800&cbr=1&q=90&fit=max","audio":""},{"link":"https:\/\/www.vogue.com\/article\/a-first-look-at-tate-mcraes-fashion-makeover-for-her-latest-music-video-sports-car","title":"From Pop Star to Fashion Icon\u2014An Exclusive First Look at Tate McRae\u2019s Fashion Makeover for Her Latest Music Video \u201cSports Car\u201d","ch":"Vogue","date":1737608400,"image":"https:\/\/assets.vogue.com\/photos\/6791621edda0c93f983f76ad\/master\/pass\/000046570028.jpg","audio":""},{"link":"https:\/\/hypebeast.com\/2025\/1\/gant-seasonal-drop-2025-womenswear-menswear-release-info","title":"GANT Readies Timeless Wardrobe Staples in New Seasonal Drop","ch":"Hypebeast","date":1737608177,"image":"https:\/\/image-cdn.hypb.st\/https%3A%2F%2Fhypebeast.com%2Fimage%2F2025%2F01%2F22%2Fgant-new-arrivals-2025-release-info-000.jpg?w=800&cbr=1&q=90&fit=max","audio":""},{"link":"https:\/\/www.fashionsnap.com\/article\/2025-01-23\/the-stand-ragelow\/","title":"\u30d9\u30a4\u30af\u30eb\u30fc\u30ba\u306e\u30ae\u30d5\u30c8\u30b7\u30e7\u30c3\u30d7\u300cTHE STAND\u300d\u304c\u30a2\u30fc\u30c6\u30a3\u30b9\u30c8 ragelow\u3068\u30b3\u30e9\u30dc\u30b3\u30ec\u30af\u30b7\u30e7\u30f3\u3092\u767a\u58f2","ch":"FASHIONSNAP\u3010\u30d5\u30a1\u30c3\u30b7\u30e7\u30f3\u30b9\u30ca\u30c3\u30d7\u3011","date":1737605991,"image":"https:\/\/fashionsnap-assets.com\/asset\/format=auto,fit=crop,width=300,height=300\/article\/images\/2025\/01\/20241216_JOURNALSTANDARD_20384-cb7f9e4f-72fb-42f2-9095-7fc0ee3b9427.jpg","audio":""},{"link":"https:\/\/www.fashionsnap.com\/collection\/coperni\/2025-pre-fall-collection\/","title":" COPERNI 2025 Pre-Fall \u30b3\u30ec\u30af\u30b7\u30e7\u30f3 ","ch":"FASHIONSNAP\u3010\u30d5\u30a1\u30c3\u30b7\u30e7\u30f3\u30b9\u30ca\u30c3\u30d7\u3011","date":1737605164,"image":"https:\/\/fashionsnap-assets.com\/asset\/format=auto,fit=crop,width=300,height=300\/collection\/images\/2025\/01\/coperni_25pf_00001-f681935a-0559-48d3-862b-6b1d7dbd9bd4.jpg","audio":""},{"link":"https:\/\/www.fashionsnap.com\/collection\/ami-paris\/2025aw\/","title":" AMI PARIS 2025AW \u30b3\u30ec\u30af\u30b7\u30e7\u30f3 ","ch":"FASHIONSNAP\u3010\u30d5\u30a1\u30c3\u30b7\u30e7\u30f3\u30b9\u30ca\u30c3\u30d7\u3011","date":1737604829,"image":"https:\/\/fashionsnap-assets.com\/asset\/format=auto,fit=crop,width=300,height=300\/collection\/images\/2025\/01\/ami-paris_25aw_00001-6400ee99-fe74-4cc5-8a4f-f2333663abe3.jpg","audio":""},{"link":"https:\/\/www.fashionsnap.com\/article\/2025-01-23\/rirekisho-how-to\/","title":"\u30d5\u30a1\u30c3\u30b7\u30e7\u30f3\u696d\u754c\u306e\u5c65\u6b74\u66f8\u306f\u3069\u3046\u66f8\u304f\uff1f\u3000\u670d\u88c5\u304b\u3089\u9aea\u578b\u3001\u81ea\u5df1PR\u307e\u3067","ch":"FASHIONSNAP\u3010\u30d5\u30a1\u30c3\u30b7\u30e7\u30f3\u30b9\u30ca\u30c3\u30d7\u3011","date":1737604771,"image":"https:\/\/fashionsnap-assets.com\/asset\/format=auto,fit=crop,width=300,height=300\/article\/images\/2025\/01\/rirekisyo-202501228-3b76f9e0-d789-45c0-bdcf-77dc2b6f45c1.jpg","audio":""},{"link":"https:\/\/www.fashionsnap.com\/article\/2025-01-23\/nike-air-superfly\/","title":"\u30ca\u30a4\u30ad\u304c\u300c\u30a8\u30a2\u30b9\u30fc\u30d1\u30fc\u30d5\u30e9\u30a4\u300d\u3092\u5fa9\u523b\u3001\u30b8\u30e5\u30f3\u30e4 \u30ef\u30bf\u30ca\u30d9\u3068\u3082\u30b3\u30e9\u30dc\u3057\u305f\u30c8\u30ec\u30fc\u30cb\u30f3\u30b0\u30b7\u30e5\u30fc\u30ba","ch":"FASHIONSNAP\u3010\u30d5\u30a1\u30c3\u30b7\u30e7\u30f3\u30b9\u30ca\u30c3\u30d7\u3011","date":1737601253,"image":"https:\/\/fashionsnap-assets.com\/asset\/format=auto,fit=crop,width=300,height=300\/article\/images\/2025\/01\/nike-air-super-fly-4-308940f3-4b61-4744-a6b3-f70438640226.jpg","audio":""},{"link":"https:\/\/www.fashionsnap.com\/streetstyle\/2025-01-23\/418769\/","title":" \u30b9\u30c8\u30ea\u30fc\u30c8\u30b9\u30bf\u30a4\u30eb: Job: \u7f8e\u5bb9\u5e2b ","ch":"FASHIONSNAP\u3010\u30d5\u30a1\u30c3\u30b7\u30e7\u30f3\u30b9\u30ca\u30c3\u30d7\u3011","date":1737600652,"image":"","audio":""},{"link":"https:\/\/hypebeast.com\/2025\/1\/walter-van-beirendonck-fw25-paris-fashion-week-collection","title":"Aliens Come In Peace at Walter Van Beirendonck FW25","ch":"Hypebeast","date":1737600122,"image":"https:\/\/image-cdn.hypb.st\/https%3A%2F%2Fhypebeast.com%2Fimage%2F2025%2F01%2F22%2Fwalter-van-beirendonck-fw25-paris-fashion-week-collection-000.jpg?w=800&cbr=1&q=90&fit=max","audio":""},{"link":"https:\/\/www.fashionsnap.com\/article\/2025-01-23\/wolford-isetanshinjuku-close\/","title":"\u30a6\u30a9\u30eb\u30d5\u30a9\u30fc\u30c9\u4f0a\u52e2\u4e39\u65b0\u5bbf\u5e97\u304c\u9589\u5e97\u3000\u6b8b\u308b\u5e97\u8217\u306f\u677e\u5c4b\u9280\u5ea7\u5e97\u306e\u307f\u306b","ch":"FASHIONSNAP\u3010\u30d5\u30a1\u30c3\u30b7\u30e7\u30f3\u30b9\u30ca\u30c3\u30d7\u3011","date":1737599989,"image":"https:\/\/fashionsnap-assets.com\/asset\/format=auto,fit=crop,width=300,height=300\/article\/images\/2025\/01\/close-20250123-5b1e770e-fbfc-4a19-8d32-4df76a59f055.jpg","audio":""},{"link":"https:\/\/www.fashionsnap.com\/article\/2025-01-23\/sinn-purete-femcare\/","title":"\u300c\u30b7\u30f3 \u30d4\u30e5\u30eb\u30c6\u300d\u304b\u3089\u751f\u7406\u6642\u306e\u4e0d\u8abf\u306b\u7740\u76ee\u3057\u305f\u30d5\u30ec\u30b0\u30e9\u30f3\u30b9\u304c\u767b\u5834\u3000\u5fc3\u306e\u4e71\u308c\u306b\u9999\u308a\u3067\u30a2\u30d7\u30ed\u30fc\u30c1","ch":"FASHIONSNAP\u3010\u30d5\u30a1\u30c3\u30b7\u30e7\u30f3\u30b9\u30ca\u30c3\u30d7\u3011","date":1737599407,"image":"https:\/\/fashionsnap-assets.com\/asset\/format=auto,fit=crop,width=300,height=300\/article\/images\/2025\/01\/sinn-purete-femcare-dff52d7c-de9b-4bef-8bba-11bc9011f55e.jpg","audio":""},{"link":"https:\/\/hypebeast.com\/2025\/1\/whiz-limited-the-future-is-mine-ss25-collection-lookbook-spring-summer-2025-release-info","title":"WHIZ LIMITED SS25 Is Well-Equipped for the Weather","ch":"Hypebeast","date":1737597664,"image":"https:\/\/image-cdn.hypb.st\/https%3A%2F%2Fhypebeast.com%2Fimage%2F2025%2F01%2F22%2Fwhiz-limited-the-future-is-mine-ss25-collection-lookbook-spring-summer-2025-release-info-0.jpg?w=800&cbr=1&q=90&fit=max","audio":""},{"link":"https:\/\/www.fashionsnap.com\/collection\/lgn-louis-gabriel-nouchi\/2025aw\/","title":" LGN LOUIS GABRIEL NOUCHI 2025AW \u30b3\u30ec\u30af\u30b7\u30e7\u30f3 ","ch":"FASHIONSNAP\u3010\u30d5\u30a1\u30c3\u30b7\u30e7\u30f3\u30b9\u30ca\u30c3\u30d7\u3011","date":1737597518,"image":"https:\/\/fashionsnap-assets.com\/asset\/format=auto,fit=crop,width=300,height=300\/collection\/images\/2025\/01\/lgn-louis-gabriel-nouchi_25aw_00001-acd105a7-773b-4467-b07c-ea70b3a428e1.jpg","audio":""},{"link":"https:\/\/hypebeast.com\/2025\/1\/needles-fw25-collection-campaign-release-date-info","title":"NEEDLES FW25 Evokes Tokyo's Expressive Ethos","ch":"Hypebeast","date":1737597470,"image":"https:\/\/image-cdn.hypb.st\/https%3A%2F%2Fhypebeast.com%2Fimage%2F2025%2F01%2F22%2Fneedles-fw25-collection-campaign-release-date-info-0.jpg?w=800&cbr=1&q=90&fit=max","audio":""},{"link":"https:\/\/www.fashionsnap.com\/collection\/songzio\/2025aw\/","title":" SONGZIO 2025AW \u30b3\u30ec\u30af\u30b7\u30e7\u30f3 ","ch":"FASHIONSNAP\u3010\u30d5\u30a1\u30c3\u30b7\u30e7\u30f3\u30b9\u30ca\u30c3\u30d7\u3011","date":1737597391,"image":"https:\/\/fashionsnap-assets.com\/asset\/format=auto,fit=crop,width=300,height=300\/collection\/images\/2025\/01\/songzio_25aw_00001-c685903d-e24e-4ef2-9990-3a6b92f8a2f5.jpg","audio":""},{"link":"https:\/\/hypebeast.com\/2025\/1\/south2-west8-fw25-release-date-info","title":"SOUTH2 WEST8 Dresses Cozy Mountain Explorers For FW25","ch":"Hypebeast","date":1737596540,"image":"https:\/\/image-cdn.hypb.st\/https%3A%2F%2Fhypebeast.com%2Fimage%2F2025%2F01%2F22%2Fsouth2-west8-fw25-release-date-info-0.jpg?w=800&cbr=1&q=90&fit=max","audio":""},{"link":"https:\/\/hypebeast.com\/2025\/1\/lemaire-fw25-paris-fashion-week-collection","title":"Effortless Wearability Strikes Again for Lemaire FW25","ch":"Hypebeast","date":1737596163,"image":"https:\/\/image-cdn.hypb.st\/https%3A%2F%2Fhypebeast.com%2Fimage%2F2025%2F01%2F22%2Flemaire-fw25-paris-fashion-week-collection-000.jpg?w=800&cbr=1&q=90&fit=max","audio":""},{"link":"https:\/\/www.modernnotoriety.com\/infinite-archives-air-jordan-17-low-release-date\/","title":"Easy Otabor Teases Infinite Archives x Air Jordan 17 Low Collab","ch":"Modern Notoriety","date":1737595327,"image":"","audio":""},{"link":"https:\/\/www.vogue.com\/slideshow\/celebrity-inspired-mens-outfits-to-help-your-boyfriend-level-up-his-style","title":"Celebrity-Inspired Men\u2019s Outfits to Help Your Boyfriend Level Up His Style","ch":"Vogue","date":1737591200,"image":"https:\/\/assets.vogue.com\/photos\/6791483252ba635d4fead53b\/master\/pass\/Holding%20Collage.jpg","audio":""},{"link":"https:\/\/www.vogue.com\/article\/editor-picks-spring-summer-2025-trends","title":"9 Spring 2025 Trends Vogue Editors Can\u2019t Wait to Shop","ch":"Vogue","date":1737586309,"image":"https:\/\/assets.vogue.com\/photos\/66fc010aa041bfcc9cca360b\/master\/pass\/Chanel_SS25_Backstage_Acielle_24.jpg","audio":""},{"link":"https:\/\/www.modernnotoriety.com\/action-bronson-new-balance-990v6-amazonia-release-date\/","title":"Action Bronson Previews New Balance 990v6 \u201cAmaz\u00f5nia\u201d Collab","ch":"Modern Notoriety","date":1737585999,"image":"","audio":""},{"link":"https:\/\/www.vogue.com\/article\/one-of-them-days-film-stakes-keke-palmer-sza","title":"\u2018One of Them Days\u2019 Is the Rare Buddy Comedy With Actual Stakes","ch":"Vogue","date":1737585328,"image":"https:\/\/assets.vogue.com\/photos\/67917220b55f6558c29c951b\/master\/pass\/MCDONOF_TR005.jpg","audio":""},{"link":"https:\/\/footwearnews.com\/fashion\/celebrity-style\/julia-garner-crystal-gedebe-anitta-pumps-today-show-1234760042\/","title":"Julia Garner Goes Monochromatic In Emerald Jumpsuit and Crystal Gedebe Pumps to Promote Horror Film \u2018Wolf Man\u2019 on \u2018Today\u2019","ch":"Fashion \u2013 Footwear News","date":1737585222,"image":"https:\/\/footwearnews.com\/wp-content\/uploads\/2025\/01\/julia-garner.jpg","audio":""},{"link":"https:\/\/www.vogue.com\/article\/hailey-bieber-reviving-pantless-trend-2025","title":"Hailey Bieber Is Reviving the Pantless Trend in 2025","ch":"Vogue","date":1737584414,"image":"https:\/\/assets.vogue.com\/photos\/6791668a38c140951731f0d3\/master\/pass\/BGUS_3129596_001.jpg","audio":""},{"link":"https:\/\/footwearnews.com\/fashion\/celebrity-style\/jt-grey-fendi-cinderella-lucite-platform-stilettos-instagram-1234760188\/","title":"JT Rewears Archival Grey Fendi Cinderella Lucite Platform Stilettos for FKA Twigs \u2018Eusexua\u2019 Party","ch":"Fashion \u2013 Footwear News","date":1737583791,"image":"https:\/\/footwearnews.com\/wp-content\/uploads\/2025\/01\/JT-fendi-heels.jpg","audio":""},{"link":"https:\/\/hypebeast.com\/2025\/1\/beams-plus-limited-new-york-nyc-pop-up-store-opening-information","title":"BEAMS PLUS To Host NYC Pop-Up Shop at Noah's Flagship","ch":"Hypebeast","date":1737583352,"image":"https:\/\/image-cdn.hypb.st\/https%3A%2F%2Fhypebeast.com%2Fimage%2F2025%2F01%2F22%2Fbeams-plus-limited-new-york-nyc-pop-up-store-opening-information-0.jpg?w=800&cbr=1&q=90&fit=max","audio":""},{"link":"https:\/\/footwearnews.com\/fashion\/celebrity-style\/naomi-watts-prada-slingback-pumps-kelly-clarkson-show-1234760171\/","title":"Naomi Watts Proves Slingbacks Trend Is Here to Stay While Promoting New Book \u2018Dare I Say It: Everything I Wish I\u2019d Known About Menopause\u2019","ch":"Fashion \u2013 Footwear News","date":1737581681,"image":"https:\/\/footwearnews.com\/wp-content\/uploads\/2025\/01\/naomi-watts.jpg","audio":""},{"link":"https:\/\/www.vogue.com\/article\/victoria-beckham-soap-nails","title":"Victoria Beckham Tries Out 2025's Biggest Nail Trend","ch":"Vogue","date":1737581400,"image":"https:\/\/assets.vogue.com\/photos\/67903dc2646e990200a5a10b\/master\/pass\/Snapinst.app_471958280_18488369071021416_8262496568086760629_n_1080.jpg","audio":""},{"link":"https:\/\/footwearnews.com\/gallery\/lucy-lius-best-shoe-moments-photos\/","title":"Lucy Liu\u2019s Best Shoe Moments Over the Years [PHOTOS]","ch":"Fashion \u2013 Footwear News","date":1737578629,"image":"https:\/\/footwearnews.com\/wp-content\/uploads\/2024\/04\/Liu.jpg","audio":""},{"link":"https:\/\/footwearnews.com\/gallery\/kai-trump-shoe-moments-photos\/","title":"Kai Trump\u2019s Best Shoe Moments So Far [PHOTOS]","ch":"Fashion \u2013 Footwear News","date":1737577189,"image":"https:\/\/footwearnews.com\/wp-content\/uploads\/2025\/01\/Kai-Trump.jpg","audio":""},{"link":"https:\/\/hypebeast.com\/2025\/1\/bal-ss25-spring-summer-2025-lookbook-collection-release-info-umbro-diemme-russell-athletic","title":"BAL Expands Its Color Palette for SS25","ch":"Hypebeast","date":1737574739,"image":"https:\/\/image-cdn.hypb.st\/https%3A%2F%2Fhypebeast.com%2Fimage%2F2025%2F01%2F22%2Fbal-ss25-spring-summer-2025-lookbook-collection-release-info-umbro-diemme-russell-athletic-0.jpg?w=800&cbr=1&q=90&fit=max","audio":""},{"link":"https:\/\/stupiddope.com\/2025\/01\/daiwa-pier39-spring-summer-2025-90s-nostalgia-meets-outdoor-innovation\/","title":"DAIWA PIER39 Spring\/Summer 2025: \u201890s Nostalgia Meets Outdoor Innovation","ch":"Fashion + Style Archives | stupidDOPE","date":1737574569,"image":"https:\/\/stupiddope.com\/wp-content\/uploads\/2025\/01\/DAIWA-PIER39-00001.jpeg","audio":""},{"link":"https:\/\/stupiddope.com\/2025\/01\/ssz-unveils-no-operation-collection-for-spring-summer-2025\/","title":"SSZ Unveils \u201cNo Operation\u201d Collection for Spring\/Summer 2025","ch":"Fashion + Style Archives | stupidDOPE","date":1737574378,"image":"https:\/\/stupiddope.com\/wp-content\/uploads\/2025\/01\/SSZ-Unveils-22No-Operation22-Collection-00006.jpeg","audio":""},{"link":"https:\/\/hypebeast.com\/2025\/1\/choose-your-outerwear-grails-from-rick-owens-thom-browne-and-more-on-hbx-archives","title":"Choose Your Outerwear Grails from Rick Owens, Thom Browne and More on HBX Archives","ch":"Hypebeast","date":1737572973,"image":"https:\/\/image-cdn.hypb.st\/https%3A%2F%2Fhypebeast.com%2Fimage%2F2025%2F01%2F22%2Fhbx-archives-outerwear-1.jpg?w=800&cbr=1&q=90&fit=max","audio":""},{"link":"https:\/\/footwearnews.com\/fashion\/celebrity-style\/kai-trump-badgley-mischka-silver-embellished-sandal-heels-1234760062\/","title":"All About the Discontinued Embellished Badgley Mischka Silver Sandal Heels Kai Trump Keeps Wearing","ch":"Fashion \u2013 Footwear News","date":1737570662,"image":"https:\/\/footwearnews.com\/wp-content\/uploads\/2025\/01\/BeFunky-collage3-10.jpg","audio":""},{"link":"https:\/\/hypebeast.com\/2025\/1\/acne-studios-fw25-menswear-collection-release-info","title":"Acne Studios FW25 Unravels The Everyman","ch":"Hypebeast","date":1737570211,"image":"https:\/\/image-cdn.hypb.st\/https%3A%2F%2Fhypebeast.com%2Fimage%2F2025%2F01%2F22%2Facne-studios-fw25-menswear-collection-release-info-0.jpg?w=800&cbr=1&q=90&fit=max","audio":""},{"link":"https:\/\/footwearnews.com\/gallery\/pharrell-williams-helen-lasichanhs-couple-style-photos\/","title":"Pharrell Williams and Wife Helen Lasichanh\u2019s Couple Style [PHOTOS]","ch":"Fashion \u2013 Footwear News","date":1737568331,"image":"https:\/\/footwearnews.com\/wp-content\/uploads\/2025\/01\/Helen-Lasichanh-and-Pharrell-Williams.jpg","audio":""},{"link":"https:\/\/www.modernnotoriety.com\/jae-tips-saucony-grid-jazz-9-collab-i-love-you-but-im-busy-release-date\/","title":"Jae Tips Unveils Saucony Grid Jazz 9 Collab: \u201cI Love You But I\u2019m Busy\u201d","ch":"Modern Notoriety","date":1737566120,"image":"","audio":""},{"link":"https:\/\/footwearnews.com\/fashion\/celebrity-style\/julia-fox-pointy-pumps-ballet-flat-bag-watch-what-happens-1234759876\/","title":"Julia Fox Showcases Outrageously Pointy Pumps & Bag Adorned with a Ballet Flat While Promoting \u2018Presence\u2019 in NYC","ch":"Fashion \u2013 Footwear News","date":1737565011,"image":"https:\/\/footwearnews.com\/wp-content\/uploads\/2025\/01\/julia-fox-2.jpg","audio":""},{"link":"https:\/\/footwearnews.com\/fashion\/celebrity-style\/julia-fox-dsquared2-skate-moss-boots-late-night-seth-meyers-1234759859\/","title":"Julia Fox Gives No-Pants Trend a Twist With \u2018Iconic\u2019 Dsquared2\u2019s Skate Moss Boots to Promote Her New Film \u2018Presence\u2019 on \u2018Late Night with Seth Meyers\u2019","ch":"Fashion \u2013 Footwear News","date":1737564860,"image":"https:\/\/footwearnews.com\/wp-content\/uploads\/2025\/01\/julia-fox-dsquared-skate-moss.jpg","audio":""},{"link":"https:\/\/stupiddope.com\/2025\/01\/hennessey-launches-the-warhawk-a-tactical-recon-vehicle-ready-for-action\/","title":"Hennessey Launches the Warhawk: A Tactical Recon Vehicle Ready for Action","ch":"Fashion + Style Archives | stupidDOPE","date":1737561962,"image":"https:\/\/stupiddope.com\/wp-content\/uploads\/2025\/01\/Hennessey-Launches-the-Warhawk-00003.jpg","audio":""},{"link":"https:\/\/stupiddope.com\/2025\/01\/knockaround-expands-pga-tour-presence-with-mark-hubbard-and-peter-malnati\/","title":"Knockaround Expands PGA Tour Presence with Mark Hubbard and Peter Malnati","ch":"Fashion + Style Archives | stupidDOPE","date":1737561864,"image":"https:\/\/stupiddope.com\/wp-content\/uploads\/2025\/01\/20250114Knockaround_Golf_Palm_Desert_0273FINAL.jpg","audio":""},{"link":"https:\/\/stupiddope.com\/2025\/01\/walmart-x-carrots-by-anwar-carrots-the-homegrown-collection-is-here\/","title":"Walmart x Carrots by Anwar Carrots: The \u201cHomegrown\u201d Collection is Here","ch":"Fashion + Style Archives | stupidDOPE","date":1737561773,"image":"https:\/\/stupiddope.com\/wp-content\/uploads\/2025\/01\/CARROTS_WALMART-1112240197885.jpg","audio":""},{"link":"https:\/\/www.modernnotoriety.com\/louis-vuitton-buttersoft-pharrell-nigo-release-date\/","title":"Closer Look at Pharrell & NIGO\u2019s Louis Vuitton ButterSoft Sneaker","ch":"Modern Notoriety","date":1737559795,"image":"","audio":""},{"link":"https:\/\/stupiddope.com\/2025\/01\/blauer-x-pirelli-the-intersection-of-performance-and-style\/","title":"Blauer x Pirelli: The Intersection of Performance and Style","ch":"Fashion + Style Archives | stupidDOPE","date":1737555832,"image":"https:\/\/stupiddope.com\/wp-content\/uploads\/2025\/01\/look-04-2027.jpg","audio":""},{"link":"https:\/\/stupiddope.com\/2025\/01\/stone-island-elevates-performance-wear-with-membrana-3l-tc-collection\/","title":"Stone Island Elevates Performance Wear with Membrana 3L TC Collection","ch":"Fashion + Style Archives | stupidDOPE","date":1737555744,"image":"https:\/\/stupiddope.com\/wp-content\/uploads\/2025\/01\/Stone-Island-SS-025-Membrana-3L-TC_STILL-LIFE.jpg","audio":""},{"link":"https:\/\/stupiddope.com\/2025\/01\/revo-and-lexus-unite-for-a-stylish-collaboration-that-redefines-luxury-eyewear\/","title":"Revo and Lexus Unite for a Stylish Collaboration That Redefines Luxury Eyewear","ch":"Fashion + Style Archives | stupidDOPE","date":1737555656,"image":"https:\/\/stupiddope.com\/wp-content\/uploads\/2025\/01\/HF7_0167-Sideline-Sports-Photography_Lexus-Racing-USA-\u00a9-2025.jpg","audio":""},{"link":"https:\/\/stupiddope.com\/2025\/01\/thisisneverthat-x-dr-martens-collab-brings-modern-edge-to-timeless-classics\/","title":"thisisneverthat x Dr. Martens Collab Brings Modern Edge to Timeless Classics","ch":"Fashion + Style Archives | stupidDOPE","date":1737551850,"image":"https:\/\/stupiddope.com\/wp-content\/uploads\/2025\/01\/thisisneverthat-x-Dr.-Martens-00005.jpeg","audio":""},{"link":"https:\/\/stupiddope.com\/2025\/01\/malbon-golf-welcomes-minjee-lee-to-its-expanding-roster-of-lpga-ambassadors\/","title":"Malbon Golf Welcomes Minjee Lee to Its Expanding Roster of LPGA Ambassadors","ch":"Fashion + Style Archives | stupidDOPE","date":1737551530,"image":"https:\/\/stupiddope.com\/wp-content\/uploads\/2025\/01\/Malbon-Golf-Welcomes-Minjee-Lee-.jpeg","audio":""},{"link":"https:\/\/hypebeast.cn\/2025\/1\/teamlab-planets-tokyo-new-expanded-area-info","title":"\u6269\u5927 1.5 \u500d\uff01teamLab Planets TOKYO \u63a8\u51fa\u5168\u65b0\u4e92\u52a8\u4f53\u9a8c\u8bbe\u65bd","ch":"Hypebeast","date":1737536083,"image":"https:\/\/image-cdn.hypb.st\/https%3A%2F%2Fhypebeast.com%2Fwp-content%2Fblogs.dir%2F4%2Ffiles%2F2025%2F01%2F22%2Fhttps___hk.hypebeast.com_files_2025_01_22_https___hypebeast.com_image_2025_01_21_teamlab-planets-tokyo-new-expanded-area-info-001-1.jpg?w=800&cbr=1&q=90&fit=max","audio":""},{"link":"https:\/\/hypebeast.cn\/2025\/1\/joopiter-nigo-knows-pharrell-williams-knows-too-auction-announcement","title":"\u6570\u767e\u4ef6 NIGO\u3001Pharrell \u4e2a\u4eba\u6536\u85cf\u54c1\u5c06\u4e8e\u7f51\u7edc\u516c\u5f00\u62cd\u5356","ch":"Hypebeast","date":1737535773,"image":"https:\/\/image-cdn.hypb.st\/https%3A%2F%2Fhypebeast.com%2Fwp-content%2Fblogs.dir%2F4%2Ffiles%2F2025%2F01%2F22%2Fhttps___hk.hypebeast.com_files_2025_01_22_hypebeast.com_image_2025_01_21_joopiter-nigo-knows-pharrell-williams-knows-too-auction-announcement-000-1.jpg?w=800&cbr=1&q=90&fit=max","audio":""},{"link":"https:\/\/hypebeast.cn\/2025\/1\/pharrell-nigo-louis-vuitton-fw25-collaborative-paris-fashion-week-collection","title":"\u6f6e\u6d41\u5144\u5f1f\u6863\u5171\u521b\u53f2\u8bd7\uff01Pharrell \u4e0e NIGO \u503e\u5fc3\u6253\u9020 Louis Vuitton 2025 \u6700\u65b0\u79cb\u51ac\u7cfb\u5217\u5927\u79c0","ch":"Hypebeast","date":1737534847,"image":"https:\/\/image-cdn.hypb.st\/https%3A%2F%2Fhypebeast.com%2Fwp-content%2Fblogs.dir%2F4%2Ffiles%2F2025%2F01%2F22%2Fhttps___hk.hypebeast.com_files_2025_01_22_pharrell-nigo-louis-vuitton-fw25-collaborative-paris-fashion-week-collection-0.jpg?w=800&cbr=1&q=90&fit=max","audio":""},{"link":"https:\/\/hypebeast.cn\/2025\/1\/pokemon-mcdonalds-happy-meal-trading-card-game-tcg-release-info","title":"\u8054\u52a8 Pok\u00e9mon \u5361\u724c\u6e38\u620f\uff01\u7f8e\u56fd McDonald's x Pok\u00e9mon \u63a8\u51fa\u5168\u65b0\u5f00\u5fc3\u4e50\u56ed\u9910","ch":"Hypebeast","date":1737534207,"image":"https:\/\/image-cdn.hypb.st\/https%3A%2F%2Fhypebeast.com%2Fwp-content%2Fblogs.dir%2F4%2Ffiles%2F2025%2F01%2F22%2Fhttps___hk.hypebeast.com_files_2025_01_22_https___hypebeast.com_image_2025_01_21_pokemon-mcdonalds-happy-meal-trading-card-game-tcg-release-info-02-1.jpg?w=800&cbr=1&q=90&fit=max","audio":""},{"link":"https:\/\/hypebeast.cn\/2025\/1\/closer-look-auralee-new-balance-t500-fw25-paris-fashion-week-collaboration","title":"\u7387\u5148\u8fd1\u8d4f AURALEE x New Balance CT500 2025 \u6700\u65b0\u79cb\u51ac\u7cfb\u5217\u8054\u540d\u978b\u6b3e","ch":"Hypebeast","date":1737533986,"image":"https:\/\/image-cdn.hypb.st\/https%3A%2F%2Fhypebeast.com%2Fwp-content%2Fblogs.dir%2F4%2Ffiles%2F2025%2F01%2F22%2Fhttps___hypebeast.com_image_2025_01_21_closer-look-auralee-new-balance-t500-fw25-paris-fashion-week-collaboration-001-1.jpg?w=800&cbr=1&q=90&fit=max","audio":""},{"link":"https:\/\/hypebeast.cn\/2025\/1\/jennie-first-official-album-ruby-trailer-release-date","title":"\u4f17\u661f\u4e91\u96c6\uff01Jennie \u5373\u5c06\u63a8\u51fa\u4e2a\u4eba\u9996\u5f20\u5f55\u97f3\u5ba4\u4e13\u8f91\u300aRuby\u300b","ch":"Hypebeast","date":1737533719,"image":"https:\/\/image-cdn.hypb.st\/https%3A%2F%2Fhypebeast.com%2Fwp-content%2Fblogs.dir%2F4%2Ffiles%2F2025%2F01%2F22%2Fhttps___hk.hypebeast.com_files_2025_01_22_jennie-first-official-album-ruby-trailer-release-date-0-1.jpg?w=800&cbr=1&q=90&fit=max","audio":""},{"link":"https:\/\/hypebeast.cn\/2025\/1\/rose-skims","title":"Ros\u00e9 \u6027\u611f\u51fa\u955c SKIMS \u6700\u65b0\u60c5\u4eba\u8282\u7cfb\u5217\u5f62\u8c61\u7279\u8f91","ch":"Hypebeast","date":1737533459,"image":"https:\/\/image-cdn.hypb.st\/https%3A%2F%2Fhypebeast.com%2Fwp-content%2Fblogs.dir%2F4%2Ffiles%2F2025%2F01%2F22%2Fhttps___hk.hypebeast.com_files_2025_01_22_blackpink-rose-skims-valentines-day-campaig-0.jpg?w=800&cbr=1&q=90&fit=max","audio":""},{"link":"https:\/\/www.modernnotoriety.com\/cactus-plant-flea-market-louis-vuitton-fw25-release-date\/","title":"Cactus Plant Flea Market x Louis Vuitton Collab Revealed","ch":"Modern Notoriety","date":1737522447,"image":"","audio":""},{"link":"https:\/\/footwearnews.com\/gallery\/louis-vuitton-mens-fall-2025-collection-photos\/","title":"Louis Vuitton Men\u2019s Fall Winter 2025 Collection, Photos","ch":"Fashion \u2013 Footwear News","date":1737521860,"image":"https:\/\/footwearnews.com\/wp-content\/uploads\/2025\/01\/LV.jpg","audio":""},{"link":"https:\/\/www.modernnotoriety.com\/nike-sb-dunk-low-bhm-modern-cowboy-hf3058-300-release-date\/","title":"Nike SB Dunk Low \u201cModern Cowboy\u201d Dropping for Black History Month","ch":"Modern Notoriety","date":1737503794,"image":"","audio":""},{"link":"https:\/\/www.modernnotoriety.com\/air-jordan-3-pure-money-ct8532-111-release-date\/","title":"Air Jordan 3 \u201cPure Money\u201d Returns July 2025","ch":"Modern Notoriety","date":1737491574,"image":"","audio":""},{"link":"https:\/\/www.modernnotoriety.com\/nike-sb-dunk-low-aluminum-hf3063-400-release-date\/","title":"Nike SB Dunk Low \u201cAluminum\u201d Drops January 2025","ch":"Modern Notoriety","date":1737420441,"image":"","audio":""}]