[{"link":"https:\/\/hypebeast.com\/2023\/11\/olympic-games-denha-paris-fashion-collection-editorial","title":"DENHAM Becomes Official Fashion Partner of Netherlands Olympic Team for Paris 2024","ch":"Hypebeast","date":1700736349,"image":"https:\/\/image-cdn.hypb.st\/https%3A%2F%2Fhypebeast.com%2Fimage%2F2023%2F11%2Folympic-games-denha-paris-fashion-collection-editorial-0.jpg?w=800&cbr=1&q=90&fit=max","audio":""},{"link":"https:\/\/www.vogue.com\/article\/winter-sun-destinations-2023","title":"The Best Places to Visit in Winter for a Sun-Soaked Escape","ch":"Vogue","date":1700734860,"image":"https:\/\/assets.vogue.com\/photos\/63b6efc22a9e601f64a0d939\/master\/pass\/Naladhu%20Private%20Island%20Maldives%20-%20Beach%20Houses%20-%20aerial%20-%20portrait%20(1).jpg","audio":""},{"link":"https:\/\/hypebeast.com\/2023\/11\/maisie-williams-shoreditch-ski-club-jacket-collaboration-release-info","title":"Maisie Williams Designs Charity-Focused Jacket With Shoreditch Ski Club","ch":"Hypebeast","date":1700733903,"image":"https:\/\/i2.wp.com\/hypebeast.com\/image\/2023\/11\/maisie-williams-shoreditch-ski-club-jacket-collaboration-release-info-0.png?w=800","audio":""},{"link":"https:\/\/mastered.jp\/news\/celine-illuminations\/","title":"CELINE\u7684\u65b0\u6b3e\u8721\u70db\u300eILLUMINATIONS\u300f","ch":"\u30cb\u30e5\u30fc\u30b9 | Mastered\uff08\u30de\u30b9\u30bf\u30fc\u30c9\uff09","date":1700733611,"image":"","audio":""},{"link":"https:\/\/mastered.jp\/news\/valentinogaravani-freedots-2024spring\/","title":"VALENTINO GARAVANI\u7684\u65b0\u6b3e\u8fd0\u52a8\u978b\u300eFREEDOTS\u300f","ch":"\u30cb\u30e5\u30fc\u30b9 | Mastered\uff08\u30de\u30b9\u30bf\u30fc\u30c9\uff09","date":1700733045,"image":"","audio":""},{"link":"https:\/\/mastered.jp\/news\/balenciagamusic-archive\/","title":"Archive\u53c2\u4e0e\u4e86BALENCIAGA\u7684\u300aBALENCIAGA MUSIC\u300b\u3002","ch":"\u30cb\u30e5\u30fc\u30b9 | Mastered\uff08\u30de\u30b9\u30bf\u30fc\u30c9\uff09","date":1700732517,"image":"","audio":""},{"link":"https:\/\/hypebeast.com\/2023\/11\/the-north-face-baltoro-collection-release-info","title":"The North Face Pays Tribute to Spirit of Exploration with New Baltoro Collection","ch":"Hypebeast","date":1700732291,"image":"https:\/\/image-cdn.hypb.st\/https%3A%2F%2Fhypebeast.com%2Fimage%2F2023%2F11%2Fthe-north-face-baltoro-collection-release-info-000.jpg?w=800&cbr=1&q=90&fit=max","audio":""},{"link":"https:\/\/www.fashionsnap.com\/article\/fstore23aw-staff-styling-yoshiokubo\/","title":"\uff1c\u30e8\u30b7\u30aa\u30af\u30dc\u7de8\uff1e\u30d6\u30e9\u30f3\u30c9\u306e\u4e2d\u306e\u4eba\u306f\u3069\u3046\u7740\u3053\u306a\u3059\uff1f\u79c1\u7269\u30df\u30c3\u30af\u30b9\u306e\u30ea\u30a2\u30eb\u306a\u30b9\u30bf\u30a4\u30ea\u30f3\u30b0\u3092\u30c1\u30a7\u30c3\u30af","ch":"FASHIONSNAP\u3010\u30d5\u30a1\u30c3\u30b7\u30e7\u30f3\u30b9\u30ca\u30c3\u30d7\u3011","date":1700731800,"image":"https:\/\/fashionsnap-assets.com\/asset\/format=auto,fit=crop,width=300,height=300\/article\/images\/2023\/11\/yoshiokubo_staffstylingtop.jpg","audio":""},{"link":"https:\/\/hypebeast.cn\/2023\/11\/1017-alyx-9sm-nike-air-force-1-teaser","title":"1017 ALYX 9SM x Nike Air Force 1 \u6700\u65b0\u8054\u540d\u978b\u6b3e\u5373\u5c06\u767b\u573a","ch":"Hypebeast","date":1700731379,"image":"https:\/\/image-cdn.hypb.st\/https%3A%2F%2Fhypebeast.com%2Fwp-content%2Fblogs.dir%2F4%2Ffiles%2F2023%2F11%2Fhttps-hk.hypebeast.com-files-2023-11-1017-alyx-9sm-nike-air-force-1-teaser-0.jpg?w=800&cbr=1&q=90&fit=max","audio":""},{"link":"https:\/\/mastered.jp\/news\/kith-x-disney-20231124\/","title":"KITH\u548cDisney\u5408\u4f5c\u7684\u5168\u65b0\u80f6\u56ca\u7cfb\u5217\u5c06\u4e8e11\u670824\u65e5\u5f00\u59cb\u9646\u7eed\u53d1\u552e\u3002","ch":"\u30cb\u30e5\u30fc\u30b9 | Mastered\uff08\u30de\u30b9\u30bf\u30fc\u30c9\uff09","date":1700731300,"image":"","audio":""},{"link":"https:\/\/hypebeast.cn\/2023\/11\/new-balance-x-dtlr-990v4-festive-release-info","title":"DTLR \u643a\u624b New Balance \u63a8\u51fa\u9752\u5e74\u4e13\u5c5e 990v4\u300cFestive\u300d","ch":"Hypebeast","date":1700731076,"image":"https:\/\/image-cdn.hypb.st\/https%3A%2F%2Fhypebeast.com%2Fwp-content%2Fblogs.dir%2F4%2Ffiles%2F2023%2F11%2Fnew-balance-x-dtlr-990v4-festive-1-1.jpg?w=800&cbr=1&q=90&fit=max","audio":""},{"link":"https:\/\/hypebeast.cn\/2023\/11\/lebron-james-friends-and-family-unknwn-nike-lebron-21","title":"\u7387\u5148\u9884\u89c8 UNKNWN x Nike LeBron 21 \u6700\u65b0\u4eb2\u53cb\u9650\u5b9a\u8054\u540d\u914d\u8272","ch":"Hypebeast","date":1700730772,"image":"https:\/\/image-cdn.hypb.st\/https%3A%2F%2Fhypebeast.com%2Fwp-content%2Fblogs.dir%2F4%2Ffiles%2F2023%2F11%2Flebron-james-friends-and-family-unknwn-nike-lebron-21-1-1.jpg?w=800&cbr=1&q=90&fit=max","audio":""},{"link":"https:\/\/hypebeast.cn\/2023\/11\/teenage-engineering-aluminum-toy-car-release","title":"Teenage Engineering \u6b63\u5f0f\u63a8\u51fa\u5168\u65b0\u94dd\u5236\u73a9\u5177\u8f66\u300cGrip Car\u300d","ch":"Hypebeast","date":1700730466,"image":"https:\/\/image-cdn.hypb.st\/https%3A%2F%2Fhypebeast.com%2Fwp-content%2Fblogs.dir%2F4%2Ffiles%2F2023%2F11%2Fhttps-hk.hypebeast.com-files-2023-11-teenage-engineering-aluminum-toy-car-release-1.jpg?w=800&cbr=1&q=90&fit=max","audio":""},{"link":"https:\/\/mastered.jp\/news\/azabudaihillsgallery-x-minotaurinst-20231124\/","title":"AZABUDAI HILLS GALLERY \u00d7 MINOTAUR INST.\u7684\u53ef\u6301\u7eed\u5236\u670d","ch":"\u30cb\u30e5\u30fc\u30b9 | Mastered\uff08\u30de\u30b9\u30bf\u30fc\u30c9\uff09","date":1700730394,"image":"","audio":""},{"link":"https:\/\/hypebeast.cn\/2023\/11\/fragment-design-nike-air-force-1-low-black-release-date","title":"\u9ed1\u9b42\u8ffd\u52a0\uff01fragment design x Nike Air Force 1 Low \u6700\u65b0\u8054\u540d\u978b\u6b3e\u518d\u66dd\u5149","ch":"Hypebeast","date":1700730162,"image":"https:\/\/image-cdn.hypb.st\/https%3A%2F%2Fhypebeast.com%2Fwp-content%2Fblogs.dir%2F4%2Ffiles%2F2023%2F11%2Fhttps-hk.hypebeast.com-files-2023-11-fragment-design-nike-air-force-1-low-black-release-date-1-1.jpg?w=800&cbr=1&q=90&fit=max","audio":""},{"link":"https:\/\/www.fashionsnap.com\/article\/2023-11-23\/alaia-teckel\/","title":"\u30a2\u30e9\u30a4\u30a2\u304c\u65b0\u4f5c\u30d0\u30c3\u30b0\u300c\u30c6\u30b1\u30eb\u300d\u3092\u767a\u8868\u3001\u30c0\u30c3\u30af\u30b9\u30d5\u30f3\u30c9\u304c\u7740\u60f3\u6e90","ch":"FASHIONSNAP\u3010\u30d5\u30a1\u30c3\u30b7\u30e7\u30f3\u30b9\u30ca\u30c3\u30d7\u3011","date":1700730000,"image":"https:\/\/fashionsnap-assets.com\/asset\/format=auto,fit=crop,width=300,height=300\/article\/images\/2023\/11\/alaia_teckel-1.jpg","audio":""},{"link":"https:\/\/mastered.jp\/news\/jane-and-theheartbreakers-20231125\/","title":"JANE & THE HEART BREAKERS\u7684\u65b0\u4f5c\u5546\u54c1\u5c06\u4e8e11\u670825\u65e5\u53d1\u5e03\u3002","ch":"\u30cb\u30e5\u30fc\u30b9 | Mastered\uff08\u30de\u30b9\u30bf\u30fc\u30c9\uff09","date":1700729817,"image":"","audio":""},{"link":"https:\/\/mastered.jp\/news\/windandsea-x-hystericglamour-20231125\/","title":"WIND AND SEA \u00d7 HYSTERIC GLAMOUR\u7684\u7b2c\u4e94\u5f39\u5c06\u4e8e11\u670825\u65e5\u53d1\u552e\u3002","ch":"\u30cb\u30e5\u30fc\u30b9 | Mastered\uff08\u30de\u30b9\u30bf\u30fc\u30c9\uff09","date":1700729536,"image":"","audio":""},{"link":"https:\/\/mastered.jp\/news\/wildsideyohjiyamamoto-x-minedenim-20231122\/","title":"WILDSIDE YOHJI YAMAMOTO \u00d7 MINEDENIM\u7684\u7b2c\u4e8c\u6ce2","ch":"\u30cb\u30e5\u30fc\u30b9 | Mastered\uff08\u30de\u30b9\u30bf\u30fc\u30c9\uff09","date":1700727981,"image":"","audio":""},{"link":"https:\/\/www.fashionsnap.com\/article\/azabudai-hills-shop\/","title":"\u3010\u307e\u3068\u3081\u3011\u300c\u9ebb\u5e03\u53f0\u30d2\u30eb\u30ba\u300d\u30a8\u30eb\u30e1\u30b9\u304b\u3089\u30b3\u30f3\u30e9\u30f3\u30b7\u30e7\u30c3\u30d7\u307e\u3067\u30d5\u30a1\u30c3\u30b7\u30e7\u30f3\uff06\u30e9\u30a4\u30d5\u30b9\u30bf\u30a4\u30eb\u5e97\u8217\u3092\u7d39\u4ecb","ch":"FASHIONSNAP\u3010\u30d5\u30a1\u30c3\u30b7\u30e7\u30f3\u30b9\u30ca\u30c3\u30d7\u3011","date":1700727408,"image":"https:\/\/fashionsnap-assets.com\/asset\/format=auto,fit=crop,width=300,height=300\/article\/images\/2023\/11\/azabudai_hills_top_20231122.jpg","audio":""},{"link":"https:\/\/mastered.jp\/news\/nike-x-sacai-magmascape-20231206\/","title":"\u300eNIKE \u00d7 sacai Magmascape\u300f\u5c06\u4e8e12\u67086\u65e5\u8d77\u9010\u6b65\u53d1\u552e\u3002","ch":"\u30cb\u30e5\u30fc\u30b9 | Mastered\uff08\u30de\u30b9\u30bf\u30fc\u30c9\uff09","date":1700727365,"image":"","audio":""},{"link":"https:\/\/mastered.jp\/news\/andwander-x-subu-2023aw\/","title":"and wander \u00d7 SUBU\u7684\u51ac\u5b63\u51c9\u978b\u6b63\u5728\u53d1\u552e\u4e2d","ch":"\u30cb\u30e5\u30fc\u30b9 | Mastered\uff08\u30de\u30b9\u30bf\u30fc\u30c9\uff09","date":1700726639,"image":"","audio":""},{"link":"https:\/\/www.fashionsnap.com\/article\/2023-11-23\/loft-profit-increase\/","title":"\u30ed\u30d5\u30c8\u3001\u65e2\u5b58\u5e97\u30d9\u30fc\u30b9\u306e\u58f2\u4e0a\u9ad8\u304c\u30b3\u30ed\u30ca\u524d\u6c34\u6e96\u306b\u3000\u5916\u51fa\u9700\u8981\u306b\u5408\u308f\u305b\u54c1\u63c3\u3048\u5f37\u5316","ch":"FASHIONSNAP\u3010\u30d5\u30a1\u30c3\u30b7\u30e7\u30f3\u30b9\u30ca\u30c3\u30d7\u3011","date":1700726383,"image":"https:\/\/www.fashionsnap.com\/img\/noimage-330.gif","audio":""},{"link":"https:\/\/hypebeast.cn\/2023\/11\/evisen-skateboards-deluxe-2023-fall-winter-collab-items-release-info","title":"Evisen Skateboards x DELUXE \u5168\u65b0\u8054\u540d\u7cfb\u5217\u6b63\u5f0f\u767b\u573a","ch":"Hypebeast","date":1700724747,"image":"https:\/\/image-cdn.hypb.st\/https%3A%2F%2Fhypebeast.com%2Fwp-content%2Fblogs.dir%2F4%2Ffiles%2F2023%2F11%2FEvisen_Skateboards_x_DELUXE_10000.jpg?w=800&cbr=1&q=90&fit=max","audio":""},{"link":"https:\/\/hypebeast.cn\/2023\/11\/tadao-ando-mpavilion-10-queen-victoria-gardens-melbourne","title":"\u4f20\u5947\u5efa\u7b51\u5e08\u5b89\u85e4\u5fe0\u96c4\u8bbe\u8ba1\u4e4b\u82b1\u56ed\u51c9\u4ead\u6b63\u5f0f\u5f00\u653e\u53c2\u89c2","ch":"Hypebeast","date":1700724331,"image":"https:\/\/image-cdn.hypb.st\/https%3A%2F%2Fhypebeast.com%2Fwp-content%2Fblogs.dir%2F4%2Ffiles%2F2023%2F11%2Ftadao-ando-mpavilion-10-queen-victoria-gardens-melbourne1000000.jpg?w=800&cbr=1&q=90&fit=max","audio":""},{"link":"https:\/\/hypebeast.cn\/2023\/11\/puma-x-f1-asap-rocky","title":"\u62c5\u5f53 PUMA x F1 \u7cfb\u5217\u521b\u610f\u603b\u76d1\u540e\uff0cA$AP Rocky \u5982\u4f55\u4ece\u8d5b\u8f66\u6587\u5316\u53d1\u6563\u6f6e\u6d41\u7075\u611f\uff1f","ch":"Hypebeast","date":1700724217,"image":"https:\/\/image-cdn.hypb.st\/https%3A%2F%2Fhypebeast.com%2Fwp-content%2Fblogs.dir%2F4%2Ffiles%2F2023%2F11%2FHEAD-scaled.jpg?w=800&cbr=1&q=90&fit=max","audio":""},{"link":"https:\/\/hypebeast.cn\/2023\/11\/coteciel-2023-aw-lookbook-release-info","title":"c\u00f4te&ciel \u6b63\u5f0f\u53d1\u5e03 2023 \u79cb\u51ac\u7cfb\u5217 Lookbook","ch":"Hypebeast","date":1700723428,"image":"https:\/\/image-cdn.hypb.st\/https%3A%2F%2Fhypebeast.com%2Fwp-content%2Fblogs.dir%2F4%2Ffiles%2F2023%2F11%2Fcote-ciel-fw23-campaign10000.jpg?w=800&cbr=1&q=90&fit=max","audio":""},{"link":"https:\/\/www.vogue.com\/article\/dior-exhibition-2023-female-artist-collaborators","title":"In Paris, a New Dior Exhibition Celebrates Its Women Artist Collaborators","ch":"Vogue","date":1700722800,"image":"https:\/\/assets.vogue.com\/photos\/655e46d45b5d929c2526c548\/master\/pass\/_DSC9640.jpg","audio":""},{"link":"https:\/\/hypebeast.com\/2023\/11\/iter-mora-is-fashions-latest-cinematic-story","title":"ITER MORA is Fashion's Latest Cinematic Story","ch":"Hypebeast","date":1700722047,"image":"https:\/\/image-cdn.hypb.st\/https%3A%2F%2Fhypebeast.com%2Fimage%2F2023%2F11%2Fiter-mora-is-fashions-latest-cinematic-story-000.jpg?w=800&cbr=1&q=90&fit=max","audio":""},{"link":"https:\/\/hypebeast.com\/2023\/11\/cote-ciel-fw23-campaign","title":"c\u00f4te&ciel Takes to Tokyo for FW23 Campaign","ch":"Hypebeast","date":1700721049,"image":"https:\/\/image-cdn.hypb.st\/https%3A%2F%2Fhypebeast.com%2Fimage%2F2023%2F11%2Fcote-ciel-fw23-campaign-000.jpg?w=800&cbr=1&q=90&fit=max","audio":""},{"link":"https:\/\/hypebeast.com\/2023\/11\/hbx-black-friday-and-cyber-monday-sales-staff-picks-2023","title":"Staff Picks: Our Shopping List From HBX\u2019s Black Friday and Cyber Monday Sales","ch":"Hypebeast","date":1700720793,"image":"https:\/\/image-cdn.hypb.st\/https%3A%2F%2Fhypebeast.com%2Fimage%2F2023%2F11%2Fhbx-black-friday-and-cyber-monday-sales-staff-picks-2023-000.jpg?w=800&cbr=1&q=90&fit=max","audio":""},{"link":"https:\/\/www.fashionsnap.com\/article\/2023-11-23\/hobonichi-warehouse\/","title":"\u307b\u307c\u65e5\u300cMOTHER\u300d\u30d7\u30ed\u30b8\u30a7\u30af\u30c8\u304c\u30a6\u30a8\u30a2\u30cf\u30a6\u30b9\u30ab\u30f3\u30d1\u30cb\u30fc\u3068\u306e\u30b3\u30e9\u30dc\u30a2\u30a4\u30c6\u30e0\u3092\u767a\u58f2\u3001\u30ed\u30f3\u30b0\u30b9\u30ea\u30fc\u30d6T\u30b7\u30e3\u30c42\u578b\u3092\u5c55\u958b","ch":"FASHIONSNAP\u3010\u30d5\u30a1\u30c3\u30b7\u30e7\u30f3\u30b9\u30ca\u30c3\u30d7\u3011","date":1700719200,"image":"https:\/\/fashionsnap-assets.com\/asset\/format=auto,fit=crop,width=300,height=300\/article\/images\/2023\/11\/hobonichi-warehouse-20231119_006.jpg","audio":""},{"link":"https:\/\/www.fashionsnap.com\/article\/furugi-03-issue\/","title":"\u53e4\u7740\u5c4b\u306e\u76f8\u5834\u3067\u306f\u306a\u304f\u201c\u30d5\u30a1\u30c3\u30b7\u30e7\u30f3\u3068\u3057\u3066\u306e\u4fa1\u5024\u201d\u3092\u898b\u308b\u3000\u672c\u5f53\u306b\u826f\u3044\u53e4\u7740\u5c4b\u3092\u6c42\u3081\u3066\u3002\u5b66\u82b8\u5927\u5b66 ISSUE\u7de8","ch":"FASHIONSNAP\u3010\u30d5\u30a1\u30c3\u30b7\u30e7\u30f3\u30b9\u30ca\u30c3\u30d7\u3011","date":1700718118,"image":"https:\/\/fashionsnap-assets.com\/asset\/format=auto,fit=crop,width=300,height=300\/article\/images\/2023\/11\/realgood-vintage-3rd-01.jpg","audio":""},{"link":"https:\/\/hypebeast.cn\/2023\/11\/dremel-mschf-gobstomper-mschf009-dl-release-info","title":"Dremel x MSCHF Gobstomper \u5168\u65b0\u8054\u540d\u978b\u6b3e\u6b63\u5f0f\u767b\u573a","ch":"Hypebeast","date":1700716892,"image":"https:\/\/image-cdn.hypb.st\/https%3A%2F%2Fhypebeast.com%2Fwp-content%2Fblogs.dir%2F4%2Ffiles%2F2023%2F11%2Fdremel-mschf-gobstomper-mschf009-dl-release-info-0.jpg?w=800&cbr=1&q=90&fit=max","audio":""},{"link":"https:\/\/www.fashionsnap.com\/article\/2023-11-23\/groundy-tanaami-keiichi-2nd\/","title":"\u30b0\u30e9\u30a6\u30f3\u30c9 \u30ef\u30a4\u00d7\u7530\u540d\u7db2\u656c\u4e00\u3001\u7b2c2\u5f3e\u306f60\u301c70\u5e74\u4ee3\u306e\u601d\u3044\u5165\u308c\u306e\u6df1\u3044\u4f5c\u54c1\u3092\u843d\u3068\u3057\u8fbc\u3093\u3060\u30cb\u30c3\u30c83\u578b\u3092\u5c55\u958b","ch":"FASHIONSNAP\u3010\u30d5\u30a1\u30c3\u30b7\u30e7\u30f3\u30b9\u30ca\u30c3\u30d7\u3011","date":1700716734,"image":"https:\/\/fashionsnap-assets.com\/asset\/format=auto,fit=crop,width=300,height=300\/article\/images\/2023\/11\/groundy-tanaami-20231122-3.jpg","audio":""},{"link":"https:\/\/www.fashionsnap.com\/article\/2023-11-23\/ghostworld-bunkamura\/","title":"\u4f1d\u8aac\u306e\u9752\u6625\u6620\u753b\u300c\u30b4\u30fc\u30b9\u30c8\u30ef\u30fc\u30eb\u30c9\u300d\u300122\u5e74\u3076\u308a\u306b\u5287\u5834\u516c\u958b","ch":"FASHIONSNAP\u3010\u30d5\u30a1\u30c3\u30b7\u30e7\u30f3\u30b9\u30ca\u30c3\u30d7\u3011","date":1700711965,"image":"https:\/\/fashionsnap-assets.com\/asset\/format=auto,fit=crop,width=300,height=300\/article\/images\/2023\/11\/ghostworld-bunkamura-2023112001.jpg","audio":""},{"link":"https:\/\/www.fashionsnap.com\/article\/2023-11-23\/yutori-tamagotchi\/","title":"\u300c9090\u300d\u306a\u3069\u304c\u305f\u307e\u3054\u3063\u3061\u3068\u30b3\u30e9\u30dc\u3001\u30dd\u30c3\u30d7\u30a2\u30c3\u30d7\u958b\u50ac","ch":"FASHIONSNAP\u3010\u30d5\u30a1\u30c3\u30b7\u30e7\u30f3\u30b9\u30ca\u30c3\u30d7\u3011","date":1700708400,"image":"https:\/\/fashionsnap-assets.com\/asset\/format=auto,fit=crop,width=300,height=300\/article\/images\/2023\/11\/yutori-tamagotchi-231122-042.jpg","audio":""},{"link":"https:\/\/www.fashionsnap.com\/article\/2023-11-23\/salonia-skincare\/","title":"20\u4ee3\u7537\u6027\u306e\u7f8e\u5bb9\u6295\u8cc7\u304c\u5973\u6027\u3092\u4e0a\u56de\u308b\u3000\u30b5\u30ed\u30cb\u30a2\u304c\u300c\u3044\u3044\u592b\u5a66\u306e\u65e5\u300d\u306b\u5408\u308f\u305b\u30a2\u30f3\u30b1\u30fc\u30c8","ch":"FASHIONSNAP\u3010\u30d5\u30a1\u30c3\u30b7\u30e7\u30f3\u30b9\u30ca\u30c3\u30d7\u3011","date":1700708400,"image":"https:\/\/fashionsnap-assets.com\/asset\/format=auto,fit=crop,width=300,height=300\/article\/images\/2023\/11\/salonia-beauty-231121.png","audio":""},{"link":"https:\/\/hypebeast.com\/2023\/11\/oakley-fortnite-eyewear-collaboration-release-info","title":"Oakley Jumps Into Gaming With Fortnite Eyewear Collaboration","ch":"Hypebeast","date":1700707135,"image":"https:\/\/image-cdn.hypb.st\/https%3A%2F%2Fhypebeast.com%2Fimage%2F2023%2F11%2FOakley-Reveals-Fortnite-Eyewear-Collaboration-0.jpg?w=800&cbr=1&q=90&fit=max","audio":""},{"link":"https:\/\/www.vogue.com\/article\/dress-your-table-5-festive-tabletops-and-how-to-do-it-at-home","title":"Dress Your Table: 5 Festive Tabletops and How to Do it At Home","ch":"Vogue","date":1700700425,"image":"https:\/\/assets.vogue.com\/photos\/655d421f0e745a0054cf3da8\/master\/pass\/Tables_Cabana_AdrianoCisani-002.jpg","audio":""},{"link":"https:\/\/www.vogue.com\/article\/holiday-tablescapes-2023","title":"\u2019Tis the Season! 5 Design Tastemakers Share Their Ultimate Holiday Tablescapes With Vogue","ch":"Vogue","date":1700699630,"image":"https:\/\/assets.vogue.com\/photos\/655e82ef03a516d4a674d2f8\/master\/pass\/Vogue_HolidayTables_LailaGohar010.jpg","audio":""},{"link":"https:\/\/www.vogue.com\/article\/the-classic-90s-manicure-that-princess-diana-loved","title":"The Classic \u201990s Manicure That Princess Diana Loved","ch":"Vogue","date":1700695800,"image":"https:\/\/assets.vogue.com\/photos\/655e8573350107addf21c457\/master\/pass\/157130213","audio":""},{"link":"https:\/\/www.vogue.com\/article\/brit-marling-a-murder-at-the-end-of-the-world-interview","title":"Brit Marling on the Art of Storytelling and the Unexpected Prescience of \u2018A Murder at the End of the World\u2019","ch":"Vogue","date":1700695513,"image":"https:\/\/assets.vogue.com\/photos\/655e7751e525fb469e39cdb7\/master\/pass\/Unknown-1%5B1%5D.jpeg","audio":""},{"link":"https:\/\/www.vogue.com\/article\/there-is-bravery-in-the-carters-hospice-announcements","title":"There Is Bravery in The Carters\u2019 Hospice Announcements","ch":"Vogue","date":1700690492,"image":"https:\/\/assets.vogue.com\/photos\/655e3d343fd47483e691b683\/master\/pass\/GettyImages-747866.jpg","audio":""},{"link":"https:\/\/www.vogue.com\/article\/vancouver-indigenous-fashion-week-red-dress-showcase","title":"At Vancouver Indigenous Fashion Week, Red Dresses Carried a Powerful Message","ch":"Vogue","date":1700686729,"image":"https:\/\/assets.vogue.com\/photos\/655e3ea66628b52df910471b\/master\/pass\/VIFW_2023__15.jpg","audio":""},{"link":"https:\/\/www.vogue.com\/article\/am-i-chewing-correctly","title":"How Many Times Should You Chew Your Food? Experts Weigh In","ch":"Vogue","date":1700683200,"image":"https:\/\/assets.vogue.com\/photos\/653bfb2411493f1947a0a27a\/master\/pass\/Chewing_GettyImages-3239741.jpg","audio":""},{"link":"https:\/\/rain-mag.com\/jennifer-lawrence-illuminates-dior-and-saks-carousel-of-dreams-in-nyc\/","title":"Jennifer Lawrence Illuminates Dior and Saks\u2019 Carousel of Dreams in NYC","ch":"News Archives \u2013 Rain","date":1700680804,"image":"https:\/\/rain-mag.com\/wp-content\/uploads\/2022\/03\/RAIN-Logo-48x48.png","audio":""},{"link":"https:\/\/www.vogue.com\/article\/a-swifties-guide-to-football-at-thanksgiving","title":"A Swiftie's Guide to Talking About Football at Thanksgiving","ch":"Vogue","date":1700676230,"image":"https:\/\/assets.vogue.com\/photos\/655e38d8bb69b16802cbb6a2\/master\/pass\/GettyImages-1687717478.jpg","audio":""},{"link":"https:\/\/hypebeast.com\/2023\/11\/zara-studio-nicholson-collaboration-release-info","title":"Zara and Studio Nicholson Center on Conscious Design for New Collaboration","ch":"Hypebeast","date":1700675361,"image":"https:\/\/image-cdn.hypb.st\/https%3A%2F%2Fhypebeast.com%2Fimage%2F2023%2F11%2FZara-x-Studio-Nicholson-Second-Collaboration-0.jpg?w=800&cbr=1&q=90&fit=max","audio":""},{"link":"https:\/\/rain-mag.com\/parallel-universes-gucci-and-christies-digital-odyssey\/","title":"Parallel Universes: Gucci and Christie\u2019s Digital Odyssey","ch":"News Archives \u2013 Rain","date":1700674835,"image":"https:\/\/rain-mag.com\/wp-content\/uploads\/2022\/03\/RAIN-Logo-48x48.png","audio":""},{"link":"https:\/\/rain-mag.com\/giorgio-armani-unveils-aldo-fallai-per-giorgio-armani-1977-2021-exhibition-at-armani-silos\/","title":"Giorgio Armani Unveils \u201cAldo Fallai per Giorgio Armani, 1977-2021\u201d Exhibition at Armani\/Silos","ch":"News Archives \u2013 Rain","date":1700674182,"image":"https:\/\/rain-mag.com\/wp-content\/uploads\/2022\/03\/RAIN-Logo-48x48.png","audio":""},{"link":"https:\/\/hypebeast.com\/2023\/11\/willy-chavarria-fb-county-collaboration-collection-release-price-info","title":"Willy Chavarria Taps California Label FB County for Structured Workwear Collab","ch":"Hypebeast","date":1700669687,"image":"https:\/\/image-cdn.hypb.st\/https%3A%2F%2Fhypebeast.com%2Fimage%2F2023%2F11%2Fwilly-chavarria-fb-county-collaboration-collection-release-price-info-0.jpg?w=800&cbr=1&q=90&fit=max","audio":""},{"link":"https:\/\/hypebeast.com\/2023\/11\/moschino-pre-fall-2024-collection-lookbook-images","title":"Moschino Pre-Fall 2024 Has a Big Heart","ch":"Hypebeast","date":1700666905,"image":"https:\/\/image-cdn.hypb.st\/https%3A%2F%2Fhypebeast.com%2Fimage%2F2023%2F11%2Fmoschino-pre-fall-2024-collection-lookbook-images-0.jpg?w=800&cbr=1&q=90&fit=max","audio":""},{"link":"https:\/\/www.modernnotoriety.com\/kith-disney-mickey-friends-release-date\/","title":"Kith \u201cMickey & Friends\u201d Collection Celebrates 100 Years of Disney","ch":"MODERN NOTORIETY","date":1700661454,"image":"","audio":""},{"link":"https:\/\/www.modernnotoriety.com\/nike-kobe-6-protro-reverse-grinch-fv4921-600-release-date\/","title":"Official Look at the Nike Kobe 6 Protro \u201cReverse Grinch\u201d","ch":"MODERN NOTORIETY","date":1700625044,"image":"","audio":""},{"link":"https:\/\/stupiddope.com\/2023\/11\/disneys-100-years-celebrated-in-style-highsnobiety-unimatics-exclusive-mickey-watches\/","title":"Disney\u2019s 100 Years Celebrated in Style: Highsnobiety & Unimatic\u2019s Exclusive Mickey Watches","ch":"Fashion + Style Archives | stupidDOPE","date":1700571706,"image":"https:\/\/stupiddope.com\/wp-content\/uploads\/2023\/11\/Disneys-100-Years-Celebrated-in-Style-Highsnobiety-Unimatics-Exclusive-Mickey-Watches-1-e1700571527531.jpg","audio":""},{"link":"https:\/\/stupiddope.com\/2023\/11\/future-unveils-stellar-lanvin-lab-line-a-cosmic-fashion-fusion\/","title":"Future Unveils Stellar LANVIN LAB Line: A Cosmic-Fashion Fusion","ch":"Fashion + Style Archives | stupidDOPE","date":1700570892,"image":"https:\/\/stupiddope.com\/wp-content\/uploads\/2023\/11\/Future-Unveils-Stellar-LANVIN-LAB-Line-A-Cosmic-Fashion-Fusion-5-e1700570844793.jpg","audio":""},{"link":"https:\/\/www.modernnotoriety.com\/patta-new-balance-991v2-u991pd2-release-date\/","title":"Patta x New Balance 991v2 Dropping In Two Colorways","ch":"MODERN NOTORIETY","date":1700493915,"image":"","audio":""},{"link":"https:\/\/stupiddope.com\/2023\/11\/rihannas-creeper-phatty-a-bold-comeback-of-the-iconic-sneaker\/","title":"Rihanna\u2019s Creeper Phatty: A Bold Comeback of the Iconic Sneaker","ch":"Fashion + Style Archives | stupidDOPE","date":1700493275,"image":"https:\/\/stupiddope.com\/wp-content\/uploads\/2023\/11\/Rihannas-Creeper-Phatty-A-Bold-Comeback-of-the-Iconic-Sneaker-15.jpg","audio":""},{"link":"https:\/\/www.modernnotoriety.com\/powerpuff-girls-nike-sb-dunk-low-release-date\/","title":"The Powerpuff Girls x Nike SB Dunk Low Collection","ch":"MODERN NOTORIETY","date":1700492044,"image":"","audio":""},{"link":"https:\/\/stupiddope.com\/2023\/11\/the-ultimate-fusion-nike-x-sacai-x-jean-paul-gaultiers-vaporwaffle-release\/","title":"The Ultimate Fusion: Nike x sacai x Jean Paul Gaultier\u2019s Vaporwaffle Release","ch":"Fashion + Style Archives | stupidDOPE","date":1700488518,"image":"https:\/\/stupiddope.com\/wp-content\/uploads\/2023\/11\/The-Ultimate-Fusion-1-Nike-x-sacai-x-Jean-Paul-Gaultiers-Vaporwaffle-Release.jpg","audio":""},{"link":"https:\/\/stupiddope.com\/2023\/11\/richard-milles-rm-21-02-tourbillon-aerodyne-a-monochromatic-marvel\/","title":"Richard Mille\u2019s RM 21-02 Tourbillon Aerodyne: A Monochromatic Marvel","ch":"Fashion + Style Archives | stupidDOPE","date":1700487331,"image":"https:\/\/stupiddope.com\/wp-content\/uploads\/2023\/11\/Richard-Milles-RM-21-02-Tourbillon-Aerodyne-A-Monochromatic-Marvel.jpg","audio":""},{"link":"https:\/\/stupiddope.com\/2023\/11\/clothsurgeons-from-the-row-to-the-road-a-fashion-fusion\/","title":"clothsurgeon\u2019s \u2018FROM THE ROW TO THE ROAD\u2019: A Fashion Fusion","ch":"Fashion + Style Archives | stupidDOPE","date":1700486807,"image":"https:\/\/stupiddope.com\/wp-content\/uploads\/2023\/11\/clothsurgeons-FROM-THE-ROW-TO-THE-ROAD-A-Fashion-Fusion-3-1-e1700486738522.jpg","audio":""},{"link":"https:\/\/stupiddope.com\/2023\/11\/aapenows-fall-winter-2023-collection-unleashes-retro-infused-streetwear-magic\/","title":"AAPENOW\u2019s Fall\/Winter 2023 Collection Unleashes Retro-Infused Streetwear Magic","ch":"Fashion + Style Archives | stupidDOPE","date":1700403371,"image":"https:\/\/stupiddope.com\/wp-content\/uploads\/2023\/11\/Experience-the-Vibes-AAPENOWs-FallWinter-2023-Collection-Unleashes-Retro-Infused-Streetwear-Magic-15-e1700403341476.jpg","audio":""},{"link":"https:\/\/stupiddope.com\/2023\/11\/guccis-gift-to-you-a-magical-christmas-collection\/","title":"Gucci\u2019s Gift to You: A Magical Christmas Collection!","ch":"Fashion + Style Archives | stupidDOPE","date":1700398502,"image":"https:\/\/stupiddope.com\/wp-content\/uploads\/2023\/11\/Guccis-Gift-to-You-A-Magical-Christmas-Collection-8-e1700398475416.jpg","audio":""},{"link":"https:\/\/stupiddope.com\/2023\/11\/discover-the-hyped-up-fragment-design-x-anti-social-social-club-fall-2023-collection\/","title":"Discover the Hyped-Up fragment design x Anti Social Social Club Fall 2023 Collection!","ch":"Fashion + Style Archives | stupidDOPE","date":1700313934,"image":"https:\/\/stupiddope.com\/wp-content\/uploads\/2023\/11\/Discover-the-Hyped-Up-fragment-design-x-Anti-Social-Social-Club-Fall-2023-Collection-1.jpg","audio":""},{"link":"https:\/\/stupiddope.com\/2023\/11\/amiris-pre-spring-2024-campaign-a-journey-into-americana-elegance\/","title":"AMIRI\u2019s Pre-Spring 2024 Campaign: A Journey into Americana Elegance","ch":"Fashion + Style Archives | stupidDOPE","date":1700312876,"image":"https:\/\/stupiddope.com\/wp-content\/uploads\/2023\/11\/AMIRIs-Pre-Spring-2024-Campaign-A-Journey-into-Americana-Elegance-2-e1700312844782.jpg","audio":""},{"link":"https:\/\/www.modernnotoriety.com\/air-jordan-9-powder-blue-og-fq8992-101-release-date\/","title":"Air Jordan 9 \u201cPowder Blue\u201d Returning in OG Form","ch":"MODERN NOTORIETY","date":1700265161,"image":"","audio":""},{"link":"https:\/\/www.modernnotoriety.com\/nike-dunk-low-waffle-fz4041-744-release-date\/","title":"Nike Is Dropping a Waffle-Inspired Dunk Low","ch":"MODERN NOTORIETY","date":1700261532,"image":"","audio":""},{"link":"https:\/\/www.modernnotoriety.com\/rayssa-leal-nike-sb-dunk-low-fz5251-001-release-date\/","title":"Rayssa Leal Is Getting Her Own Nike SB Dunk Low","ch":"MODERN NOTORIETY","date":1700254721,"image":"","audio":""},{"link":"https:\/\/www.modernnotoriety.com\/nike-kobe-6-protro-2-8-24-pack-release-date\/","title":"Nike Kobe 8 Protro \u201c2-8-24\u201d Pack Revealed","ch":"MODERN NOTORIETY","date":1700251080,"image":"","audio":""}]